fluxus/__init__.py
fluxus/_consumer.py
fluxus/_flow.py
fluxus/_passthrough.py
fluxus/_producer.py
fluxus/_transformer.py
fluxus/_warning.py
fluxus/py.typed
fluxus/core/__init__.py
fluxus/core/_base.py
fluxus/core/_chained_base_.py
fluxus/core/_concurrent.py
fluxus/core/_conduit.py
fluxus/core/producer/__init__.py
fluxus/core/producer/_chained_.py
fluxus/core/producer/_producer_base.py
fluxus/core/producer/_simple.py
fluxus/core/transformer/__init__.py
fluxus/core/transformer/_chained_.py
fluxus/core/transformer/_simple.py
fluxus/core/transformer/_transformer_base.py
fluxus/functional/__init__.py
fluxus/functional/_functions.py
fluxus/functional/_result.py
fluxus/functional/conduit/__init__.py
fluxus/functional/conduit/_conduit.py
fluxus/functional/conduit/_consumer.py
fluxus/functional/conduit/_producer.py
fluxus/functional/conduit/_step.py
fluxus/functional/product/__init__.py
fluxus/functional/product/_product.py
fluxus/lineage/__init__.py
fluxus/lineage/_label.py
fluxus/lineage/_lineage.py
fluxus/simple/__init__.py
fluxus/simple/_simple.py
fluxus/util/__init__.py
fluxus/util/_repr.py
fluxus/viz/__init__.py
fluxus/viz/_flow.py
fluxus/viz/_graph.py
fluxus/viz/_timeline.py
fluxus/viz/base/__init__.py
fluxus/viz/base/_style.py
fluxus-1.0.3.dist-info/LICENSE
fluxus-1.0.3.dist-info/WHEEL
fluxus-1.0.3.dist-info/METADATA
fluxus-1.0.3.dist-info/RECORD
