Metadata-Version: 2.1
Name: fluxus
Version: 1.0.3
Summary: *fluxus* is designed to handle data flows in a pipeline-like manner. It provides a
Home-page: https://github.com/BCG-X-Official/fluxus
License: Apache Software License v2.0
Author: Boston Consulting Group (BCG)
Requires-Python: >=3.10,<4a
Requires-Dist: matplotlib        ~=3.6
Requires-Dist: pandas            ~=2.1
Requires-Dist: gamma-pytools     ~=3.0
Requires-Dist: typing_inspect    ~=0.7
Requires-Dist: nbsphinx                 ~= 0.9 ; extra == "dev"
Requires-Dist: sphinx                   ~= 7.2 ; extra == "dev"
Requires-Dist: sphinx-autodoc-typehints ~= 1.25 ; extra == "dev"
Requires-Dist: pydata-sphinx-theme      ~= 0.15.1 ; extra == "dev"
Requires-Dist: packaging                ~= 24.1 ; extra == "dev"
Requires-Dist: ipywidgets               ~= 8.1 ; extra == "dev"
Requires-Dist: jupyterlab               ~= 4.2 ; extra == "dev"
Requires-Dist: notebook                 ~= 7.2 ; extra == "dev"
Requires-Dist: pytest                   ~= 8.2 ; extra == "dev"
Requires-Dist: pytest-asyncio           ~= 0.23 ; extra == "dev"
Requires-Dist: pytest-cov               ~= 5.0 ; extra == "dev"
Requires-Dist: pre-commit               ~= 3.7 ; extra == "dev"
Requires-Dist: pytest                   ~= 8.2 ; extra == "testing"
Requires-Dist: pytest-cov               ~= 5.0 ; extra == "testing"
Requires-Dist: pytest-asyncio           ~= 0.23 ; extra == "testing"
Project-URL: Documentation, https://bcg-x-official.github.io/fluxus/
Project-URL: Repository, https://github.com/BCG-X-Official/fluxus
Provides-Extra: dev
Provides-Extra: testing
